{
  "pano_id": "0qR4Klbui9SsNZAzYndiJg",
  "views": {
    "view_10": [
      {
        "tree_index": "0-0",
        "image_path": "/home/utkarsh/TreeInventorization/data/views/0qR4Klbui9SsNZAzYndiJg_view10_tree0_box4.jpg",
        "confidence": 0.012265128083527088,
        "mask_data": {
          "orig_shape": [
            720,
            1024
          ],
          "encoding": "rle",
          "rle": {
            "size": [
              720,
              1024
            ],
            "counts": "R]R7<Tf0000000000000000a]OOi71lJ1PM`0T5EXI=a4_OmL_1X3d2HnKaJKP1I^NT3Q5b1o0gK[J>GS4X4Mf1c3gLbLX3^4^KlKb4Q;0000000000000000000000000000000000000PD`Ko5a4SIbLh6^3SImLg6S3THSJcN]3<YM_6W5UJj1n4VNcJQ35YGc2g5mLR4_OmGX2Q4TNU8>lG[Ob8=_G@j89WGFo83SGLi?00O10000000nPY>"
          },
          "bbox": [
            322.0,
            2.0,
            373.0,
            527.0
          ]
        }
      }
    ],
    "view_11": [
      {
        "tree_index": "1-0",
        "image_path": "/home/utkarsh/TreeInventorization/data/views/0qR4Klbui9SsNZAzYndiJg_view11_tree0_box1.jpg",
        "confidence": 0.016382459551095963,
        "mask_data": {
          "orig_shape": [
            720,
            1024
          ],
          "encoding": "rle",
          "rle": {
            "size": [
              720,
              1024
            ],
            "counts": "Ujd6m1cd000000M3F;[Oe0QOn0F;B>eN[1[Kd4XOi0VOi0\\Oe0^Oa0G:G8E;C=01O0000000000000000000000000000O100O1O1N2M3A?H8K5K5mMS2[J]FkMU:m1]FeLg:T3^4G9B>I7O100000^Vd>"
          },
          "bbox": [
            302.0,
            82.0,
            357.0,
            554.0
          ]
        }
      }
    ]
  },
  "metadata": {
    "total_views": 2,
    "total_masks": 2
  }
}