{
  "pano_id": "4YfvsSAqlt5VQMhhZVbq-A",
  "views": {
    "view_1": [
      {
        "tree_index": "0-0",
        "image_path": "/home/utkarsh/TreeInventorization/data/views/4YfvsSAqlt5VQMhhZVbq-A_view1_tree0_box4.jpg",
        "confidence": 0.02094476856291294,
        "mask_data": {
          "orig_shape": [
            720,
            1024
          ],
          "encoding": "rle",
          "rle": {
            "size": [
              720,
              1024
            ],
            "counts": "Zaj;c0j1JG5cNY2`>hMVCJG5cNY2`>hMVCJG5cNY2`>hMVCJG5cNY2`>jMSBDO90k3j=\\LnAKO61f3R>^MgAm3Y>U200000000000000000000000000000000000K5N2nH_A\\2m0Af=oMdAX1NgNR2m0_<ROiAo04bNVb0<W^O8Pc0Fn1N2N2NXkl9"
          },
          "bbox": [
            538.0,
            266.0,
            572.0,
            521.0
          ]
        }
      }
    ],
    "view_3": [
      {
        "tree_index": "1-0",
        "image_path": "/home/utkarsh/TreeInventorization/data/views/4YfvsSAqlt5VQMhhZVbq-A_view3_tree0_box0.jpg",
        "confidence": 0.07364173233509064,
        "mask_data": {
          "orig_shape": [
            720,
            1024
          ],
          "encoding": "rle",
          "rle": {
            "size": [
              720,
              1024
            ],
            "counts": "Vdj;X3Xc00000000000000000000000000000000000K500O100000j_T:"
          },
          "bbox": [
            538.0,
            358.0,
            561.0,
            461.0
          ]
        }
      }
    ],
    "view_9": [
      {
        "tree_index": "2-0",
        "image_path": "/home/utkarsh/TreeInventorization/data/views/4YfvsSAqlt5VQMhhZVbq-A_view9_tree0_box5.jpg",
        "confidence": 0.0148344486951828,
        "mask_data": {
          "orig_shape": [
            720,
            1024
          ],
          "encoding": "rle",
          "rle": {
            "size": [
              720,
              1024
            ],
            "counts": "kPn5R1^e00000000100O100O10O01O100O10O0100O10O10O0100O01O100O1O1O100O1O1O01O10O01N2N2N2O1N3N2M2L5H7POaNk\\Oc1Sc0aNg\\Oc1Wc0cN`\\Ob1^c0m0K=C:F5K7I7I:F8H9G<D7I9GP1PO?A6J5K4L7I7I3M001O0=C4K4M2fIeAZ4^>jJdA_O8d5W>gJ^BX5f=cJ]B\\5[?O10000N1fLc_Oc0^`0aNe@]OhNg0d`0JTBGo=9]BUOj=j0n3O1O1O1O1O1O1O1O100N2O010O10O010000O00100000O1O1O1O0O2L4A`0N1O002O00O0100L41O1N2O1N2N2M3N2N2O1N2O1N2O1N2O1O1O1O1O1O1O1N2O1O1N2O1O1O1O1O1O1O1N2O1O1O1O1O1O100O1O1O1O[Uk<"
          },
          "bbox": [
            270.0,
            166.0,
            438.0,
            435.0
          ]
        }
      }
    ]
  },
  "metadata": {
    "total_views": 3,
    "total_masks": 3
  }
}