{
  "pano_id": "6DU7GCpm8ycwDmr2hvbvuQ",
  "views": {
    "view_3": [
      {
        "tree_index": "0-0",
        "image_path": "/home/utkarsh/TreeInventorization/data/views/6DU7GCpm8ycwDmr2hvbvuQ_view3_tree0_box0.jpg",
        "confidence": 0.010544084943830967,
        "mask_data": {
          "orig_shape": [
            720,
            1024
          ],
          "encoding": "rle",
          "rle": {
            "size": [
              720,
              1024
            ],
            "counts": "VlS6X1Xe000000N6H4L4L4N2K5J6K5L4L4J6LO21OO000O4E<I7K5M3N2M2L5H8J5M4L3NO22M3N2N2O1N2O1O1O1O1O1O100O1O100O1O1O1O10000000RjT?"
          },
          "bbox": [
            278.0,
            350.0,
            333.0,
            465.0
          ]
        }
      }
    ],
    "view_6": [
      {
        "tree_index": "1-0",
        "image_path": "/home/utkarsh/TreeInventorization/data/views/6DU7GCpm8ycwDmr2hvbvuQ_view6_tree0_box0.jpg",
        "confidence": 0.014569825492799282,
        "mask_data": {
          "orig_shape": [
            720,
            1024
          ],
          "encoding": "rle",
          "rle": {
            "size": [
              720,
              1024
            ],
            "counts": "be]?i0<Bf0[3g3]Mc5FPFBf0[3g3]Mc5FPFBf0[3g3]Mc5FPFBf0[3g3]Mc5JjEAk0Z3b3_Mi5:dF^20RLA`0j0h1n8XOgFf2\\O\\M`0V1X9hNkFi4CfLb9aNkFo4VOgLo9ZNkF[8U9eGlFZ8T9fGmFY8S9gGoFW8Q9hG[Gm7e8SH_Hi6a7VIfHd6Z7[IjHb6V7^InH^6R7bITIX6l6hIWIU6i6lIXIR6h6oIXIP6V7bIjH^6]7\\IcHc6`7[I^Hf6d7[IXHf6j7\\IQHe6Q8\\IjGf6W8ZIfGh6Z8ZIbGh6_8YI]Gi6c8XIZGX2fMT1P;eLWGT2RNS1h:jLQGU2ZNo0e:nLlFV2aNj0c:QMgFY2iNXOk;aNWEZ2POmNo;kNkD_2UO^NV<UO`Db2YORN\\<^OWDc2@fM_;\\NTDo1g0S2LPMd;`1WDe18[Ln;U2^Ch1d0lKT<\\7mC`HV<b7jCXHZ<j7U12N1O2N19G3NOOO0O101N0I72N2N2N2fLdA^N^>_1fA^N\\>NiAUNNk1[>MmASNJn1[>KRBPNGS2Y>IZBjMAW2[>K[CNl<OXCLl<0YCLj<1\\CHh<3aCCe<7eCA_<:kC]OY<`0PDUOU<j0i4O1O1N2O:G000000UXW5"
          },
          "bbox": [
            702.0,
            82.0,
            785.0,
            477.0
          ]
        }
      }
    ],
    "view_11": [
      {
        "tree_index": "2-0",
        "image_path": "/home/utkarsh/TreeInventorization/data/views/6DU7GCpm8ycwDmr2hvbvuQ_view11_tree0_box2.jpg",
        "confidence": 0.023402178660035133,
        "mask_data": {
          "orig_shape": [
            720,
            1024
          ],
          "encoding": "rle",
          "rle": {
            "size": [
              720,
              1024
            ],
            "counts": "Z_n:c0me0000004L11O1O2M200O2N3N1N00100O1OO101N101N2N2N2N3M2N100O10O3M4L3M3L3N2M2N2VOQOP\\OQ1hc0\\OP\\Og0kc0@P\\Oc0oc0o001O1O1O1O2N2N2N1O001O1O1O1O1O1O1O1O1O2N_Mf\\OQ2Sd0M2L1NO1O1O10O306LNON002N3MPNQ\\O_1ad01O200N1OO3O10O1N10010OO002000O1OO0110O1N10O01O3M2N2O10K4L3M4L4L2N000000eaR9"
          },
          "bbox": [
            498.0,
            330.0,
            609.0,
            601.0
          ]
        }
      }
    ]
  },
  "metadata": {
    "total_views": 3,
    "total_masks": 3
  }
}