{
  "pano_id": "6vg0ov6ZOTArBxH4WbhOOA",
  "views": {
    "view_0": [
      {
        "tree_index": "0-0",
        "image_path": "/home/utkarsh/TreeInventorization/data/views/6vg0ov6ZOTArBxH4WbhOOA_view0_tree0_box0.jpg",
        "confidence": 0.023670267313718796,
        "mask_data": {
          "orig_shape": [
            720,
            1024
          ],
          "encoding": "rle",
          "rle": {
            "size": [
              720,
              1024
            ],
            "counts": "bXj>P8`>000000;E`0@m0SO6J2N1O001O001O000014K2N2N04L0OM3dG_Ck6`<TIeChNOd7\\<^IZD`6f;_I]D^6d;`I`D^6a;`IbD^6_;`IWEk5k:QJ[Ek5g:RJ\\El5Q;dISE[6b=N2O001O000O1000001N10000O10O1gLmI^CH]2[6n9bJnE^5R:cJmE]5S:eJjE\\5V:fJhEZ5X:hJgEW5Y:kJeEU5[:mJcES5]:PK`EQ5_:QK^EP5b:SK[Em4e:WKVEj4j:XKSEi4m:ZKoDh4P;^KfCnM04c0a6g;ULdCXM5e6W<\\LcCh3\\<U310004[IcCn2g<^LmCX3\\<^LVDo2[<cLnCP3_<fLgCj1iNPMk=P1gDa0g<dNY@F_3Z1^<^NgD[1\\`0IY\\o5"
          },
          "bbox": [
            674.0,
            370.0,
            750.0,
            697.0
          ]
        }
      }
    ],
    "view_5": [
      {
        "tree_index": "1-0",
        "image_path": "/home/utkarsh/TreeInventorization/data/views/6vg0ov6ZOTArBxH4WbhOOA_view5_tree0_box0.jpg",
        "confidence": 0.011641757562756538,
        "mask_data": {
          "orig_shape": [
            720,
            1024
          ],
          "encoding": "rle",
          "rle": {
            "size": [
              720,
              1024
            ],
            "counts": "nYc2h2hc0000000001O1O1O2N1O2N1O2N2N1O2N4L0000000000eMZ]Ol0mb0fNa]OS1gb0\\Ne]Oa1gc0J6L5L2O000000QTVc0"
          },
          "bbox": [
            118.0,
            350.0,
            149.0,
            457.0
          ]
        }
      }
    ],
    "view_12": [
      {
        "tree_index": "2-0",
        "image_path": "/home/utkarsh/TreeInventorization/data/views/6vg0ov6ZOTArBxH4WbhOOA_view12_tree0_box0.jpg",
        "confidence": 0.039185382425785065,
        "mask_data": {
          "orig_shape": [
            720,
            1024
          ],
          "encoding": "rle",
          "rle": {
            "size": [
              720,
              1024
            ],
            "counts": "alb9a0ke0S4[ZOZO`=R5J0O2O0O2N010O1L3L5M1mNkFjDX9X;oFXDX9j;d03K5N20000001O1O1O4L1O1O1O001O1O1O1O1O00001O001O00001O001O001O1OO100000000O100O100O100O1000000O10:F5K4L4L2N2N2M3N2M3N4J<Ch0UOd0`H[Ao5Wa0YJg_OYOOY1hoU;"
          },
          "bbox": [
            436.0,
            278.0,
            514.0,
            623.0
          ]
        }
      }
    ]
  },
  "metadata": {
    "total_views": 3,
    "total_masks": 3
  }
}