{
  "pano_id": "AbFluxBJXSpZqpJJk1GWRg",
  "views": {
    "view_3": [
      {
        "tree_index": "0-0",
        "image_path": "/home/utkarsh/TreeInventorization/data/views/AbFluxBJXSpZqpJJk1GWRg_view3_tree0_box0.jpg",
        "confidence": 0.01284857653081417,
        "mask_data": {
          "orig_shape": [
            720,
            1024
          ],
          "encoding": "rle",
          "rle": {
            "size": [
              720,
              1024
            ],
            "counts": "`gc7S2]d000000N1OM3O001O00O1O2000N2O010O10O10000O01N02O1RLTNYCk1k<WNoBj1T=XNgBi1[=XNaBi1a=XN[Bh1h=YNRBg1S>]NR@F8o1i?`Na_O39_1X`0aNX_O88X1c`0bNQ_O:8S1j`0eNj^O;9o0Pa0gNe^O<7n0Va0gNa^O=6j0]a0VN[^OP4ha0mK\\^Oo3ga0oK[^Oo3Ub0L4L4M4L3L4M2N3M1N3L4N2N3M2N2M3N10001M2O1010OIW\\OhMic0W2Z\\OhMNO`c0Z2b\\OoM[c0e1S]O[Nlb0b1X]O^Nfb0b1\\]O^Nbb0a1a]O^N^b0`1e]O`NXb0a1k]O_NUb0^1n]OaNSb0\\1o]OdNRb0Y1o]OhNRb0V1P^OjNPb0T1Q^OlNPb0R1Q^OmNQb0Q1o]OQOQb0l0Q^OTOPb0j0R^OUOoa0i0R^OVOPb0f0S^OZOna0b0U^O^Ola0?W^O@ja0<Y^ODha09[^OFfa06]^OIea06]^OHda06\\2M3OWhk<"
          },
          "bbox": [
            346.0,
            282.0,
            437.0,
            530.0
          ]
        }
      }
    ],
    "view_4": [
      {
        "tree_index": "1-0",
        "image_path": "/home/utkarsh/TreeInventorization/data/views/AbFluxBJXSpZqpJJk1GWRg_view4_tree0_box1.jpg",
        "confidence": 0.013761166483163834,
        "mask_data": {
          "orig_shape": [
            720,
            1024
          ],
          "encoding": "rle",
          "rle": {
            "size": [
              720,
              1024
            ],
            "counts": "Rg`7P1g2a3a;_L_Da3a;_L_Da3a;_L_Da3a;iLSDY3m;RMeCQ3[<YMVCl2j<]MoAa3Q>_200000oNiAiIW>S6\\B^Id=`6gBWIY=e6[1E;XOh0XOh0O1N200O1eLW@Oi?oN`Ai0a>UOfAf0Z>XOlAc0U>\\OPB`0P>@YB6h=I\\B4d=L\\B4d=L\\B4d=L\\B4bVY>"
          },
          "bbox": [
            342.0,
            258.0,
            373.0,
            521.0
          ]
        }
      }
    ]
  },
  "metadata": {
    "total_views": 2,
    "total_masks": 2
  }
}