{
  "pano_id": "B9-DaQqpPe2JEmySsTNY7Q",
  "views": {
    "view_0": [
      {
        "tree_index": "0-0",
        "image_path": "/home/utkarsh/TreeInventorization/data/views/B9-DaQqpPe2JEmySsTNY7Q_view0_tree0_box0.jpg",
        "confidence": 0.014453576877713203,
        "mask_data": {
          "orig_shape": [
            720,
            1024
          ],
          "encoding": "rle",
          "rle": {
            "size": [
              720,
              1024
            ],
            "counts": "bYe`0h4ha000000M4J501O1O001O001O001O001O001O1O001O1O005K0000000000000005K1O3M3M2N2N3M2N2N3M3M2N3M2^L[_OU1h`0cNl_On0W`0jN[@i0g?ROe@e0Ufh4"
          },
          "bbox": [
            758.0,
            330.0,
            806.0,
            505.0
          ]
        }
      }
    ],
    "view_3": [
      {
        "tree_index": "1-0",
        "image_path": "/home/utkarsh/TreeInventorization/data/views/B9-DaQqpPe2JEmySsTNY7Q_view3_tree0_box0.jpg",
        "confidence": 0.014038446359336376,
        "mask_data": {
          "orig_shape": [
            720,
            1024
          ],
          "encoding": "rle",
          "rle": {
            "size": [
              720,
              1024
            ],
            "counts": "hQn=4>j1n1X2R;nKPCj1n1X2R;nKPCj1n1X2R;nKPCj1n1X2T:QLRDa2f1_1X:C^E>b:HVE:j:NmD3S;OjD2V;OhD2X;0fD0Z;2cDO];3`DN`;3^DNb;3\\DNd;3YDOg;3UDOk;3PD0P<2jC2V<o45N2aJ\\CP1f<gMfDSO]O1o;h0iDROCMf;o0iDQOHJa;S1gDSONB_;Y1eDSO2\\O];_1bDUO:jN^;P2XDUOa>i0`AWOa>g0`AXOf>a0\\A_Oe>?\\AAa>a0`A_Oa>>`ACa>;_AFb>8_AHb>6^AKc>2]AOe>OZA3g>LXA5i>IWA7k>GVA8l>FTA:n>DSA<n>@UA>n>^OUAa0m>YOXAf0j>nNaAR1`>kNbAU1_>hNbAX1`>gN`AY1a>eNaAY1a>dNaA[1a>bNaA]1a>aN`A]1c>aN_A]1ka0N2M3N3M2N2N3M2O1M3N1N3M4M2N2N3N1N2N3M4MYgk6"
          },
          "bbox": [
            634.0,
            250.0,
            710.0,
            569.0
          ]
        }
      }
    ]
  },
  "metadata": {
    "total_views": 2,
    "total_masks": 2
  }
}