{
  "pano_id": "Bk0JN3NbFVnTKq3NYWgVFg",
  "views": {
    "view_0": [
      {
        "tree_index": "0-0",
        "image_path": "/home/utkarsh/TreeInventorization/data/views/Bk0JN3NbFVnTKq3NYWgVFg_view0_tree0_box2.jpg",
        "confidence": 0.016471752896904945,
        "mask_data": {
          "orig_shape": [
            720,
            1024
          ],
          "encoding": "rle",
          "rle": {
            "size": [
              720,
              1024
            ],
            "counts": "baY;Z1W8U2Y1kMgNU2Y1kMgNU2Y1kMgNU2Y1mMfNS2Y1QNdNP2Z1VNfNh1V1`NdNc1W1aNmNZ1P1jNoNW1m0oNPOU1i0QOROT1h0POgJbMo0]3Z4WO_JaMT1X3]4]OXJ_MW1U3a4ARJ\\M\\1S3b4DoI[M\\1R3e4GjIYMZ1V3l4FeIVMT1]3W5AaISMQ1b3^5^O^IQMo0e3c5]O[IoLk0j3j5[OVImLj0m3P6ZORIkLh0o3Z6UOkHmLe0S4b6QOeHnLe0T4h6SO[HkLb0\\4U7mNRHjL`0`4`7iNjGjL?b4i7kN[GiLg0_4Q8c0fGB\\8X71O1O1O2N001O001O0000O100N2N2K5I7G90000000000000000000000000000000000000000000000000000000000000000000SHnG\\1R8^NZH\\1f7aNaH[1_7_NmHlJOc4T78]K]Oc4MXLNh3HfL4Z3DRM8n2B[M;e2_OdM>\\2_OiMROWJRNU8j2iMnNcJhMf7X3kMlN`3R1dLiN_3V1eLdN^3NkEYOm6`0^3MWFZO^6a0a3TO`E6f02\\6:f3QOhE9`07W65Z6FjI2]6LW8K3O000000g]j8"
          },
          "bbox": [
            514.0,
            146.0,
            621.0,
            593.0
          ]
        }
      }
    ],
    "view_3": [
      {
        "tree_index": "1-0",
        "image_path": "/home/utkarsh/TreeInventorization/data/views/Bk0JN3NbFVnTKq3NYWgVFg_view3_tree0_box1.jpg",
        "confidence": 0.01464175432920456,
        "mask_data": {
          "orig_shape": [
            720,
            1024
          ],
          "encoding": "rle",
          "rle": {
            "size": [
              720,
              1024
            ],
            "counts": "d`R:\\2Td000000O1L3K5K6K4K5G9I7L4L4D;A`0E:K3cNWKRAm4S?P18D<G9M3O1O1O10000O100000000O1O1O1[OT_ObKPa0h3W1ZOf0E;I7B>E;G9H8J6Jlb\\;"
          },
          "bbox": [
            458.0,
            346.0,
            504.0,
            575.0
          ]
        }
      },
      {
        "tree_index": "2-0",
        "image_path": "/home/utkarsh/TreeInventorization/data/views/Bk0JN3NbFVnTKq3NYWgVFg_view3_tree0_box3.jpg",
        "confidence": 0.01289057545363903,
        "mask_data": {
          "orig_shape": [
            720,
            1024
          ],
          "encoding": "rle",
          "rle": {
            "size": [
              720,
              1024
            ],
            "counts": "]Ze`0X1Xe000000Le0VOm0iKYMT@3f2V3S<_NUC[2U<oMbB[N]OR4k=j3000000000000000000000000:Fd0iHoAg4R`0K=Ch0XO>Bl0TO?A9Gb0^O8He0[O:F6JUXQ5"
          },
          "bbox": [
            758.0,
            214.0,
            793.0,
            481.0
          ]
        }
      }
    ],
    "view_6": [
      {
        "tree_index": "3-0",
        "image_path": "/home/utkarsh/TreeInventorization/data/views/Bk0JN3NbFVnTKq3NYWgVFg_view6_tree0_box2.jpg",
        "confidence": 0.017499813809990883,
        "mask_data": {
          "orig_shape": [
            720,
            1024
          ],
          "encoding": "rle",
          "rle": {
            "size": [
              720,
              1024
            ],
            "counts": "fnfa0736fe0JZZO6fe0JZZO6fe0JZZO6fe0=M7I7I:F7J7I5J5L2N4L5J5L4M2M4K5L4i]ORMd`0T3d^O^M\\a0l33ZKb^OR4Ub0I2O1O2N4K1000000000002O002M8I4L3L5K=D5K2N2L3M2N2N1N4L4L4K4M4L2N3L3L5K4M2N2N3M3M4LdT[3"
          },
          "bbox": [
            806.0,
            246.0,
            870.0,
            469.0
          ]
        }
      }
    ],
    "view_9": [
      {
        "tree_index": "4-0",
        "image_path": "/home/utkarsh/TreeInventorization/data/views/Bk0JN3NbFVnTKq3NYWgVFg_view9_tree0_box2.jpg",
        "confidence": 0.020743118599057198,
        "mask_data": {
          "orig_shape": [
            720,
            1024
          ],
          "encoding": "rle",
          "rle": {
            "size": [
              720,
              1024
            ],
            "counts": "Rh\\87Yf0000000002N1O002N1O2N1O2N1O2N2N2N1O2N2N1O2N1O1O1O1O1O2N1O1O1O1O1O14L00001O010O001O010O1O001O01O01O1O10O0000001O001O1O1N2N3M3M2N2N3M3M3L3M4J7POn0H8N2N2N2N1O2N2N2N1O2N3M2N2N2RA[Lm:i3^DnL\\;U3UD]Me;@gBV1T1KQ<jNRC]1c02m<gMgB[20:c>2e@`0T?a3N1N5K00000000000O10000O100O10SNgAcKX>V4WBcKh=U4fBbK]=V4oBfKQ=V4VCgKj<V4]CfKd<V4eCcK[<Z4o2`LY^OU2ka0hMa^OFc09Qa01Z3O10001O0O2O01O000001O000001O00O11N1001OO1000000O2O0010O1O101N100O100O100000m`e:"
          },
          "bbox": [
            382.0,
            162.0,
            537.0,
            469.0
          ]
        }
      },
      {
        "tree_index": "5-0",
        "image_path": "/home/utkarsh/TreeInventorization/data/views/Bk0JN3NbFVnTKq3NYWgVFg_view9_tree0_box5.jpg",
        "confidence": 0.01290559396147728,
        "mask_data": {
          "orig_shape": [
            720,
            1024
          ],
          "encoding": "rle",
          "rle": {
            "size": [
              720,
              1024
            ],
            "counts": "SeSf03\\f02O2lYO634`d0a1E7H7I7J3L3N3L5L8F9G7I9GR1nN3N0oE"
          },
          "bbox": [
            1006.0,
            321.0,
            1023.0,
            491.0
          ]
        }
      }
    ],
    "view_11": [
      {
        "tree_index": "6-0",
        "image_path": "/home/utkarsh/TreeInventorization/data/views/Bk0JN3NbFVnTKq3NYWgVFg_view11_tree0_box6.jpg",
        "confidence": 0.013437481597065926,
        "mask_data": {
          "orig_shape": [
            720,
            1024
          ],
          "encoding": "rle",
          "rle": {
            "size": [
              720,
              1024
            ],
            "counts": "Tkbe0=Sf0000001O100011N01O01O1O1O00001O0O100O2N1O100O1O1O2N102M2O0O2O2N2N2N3M3L1N2O1O1N2O0VC"
          },
          "bbox": [
            982.0,
            388.0,
            1023.0,
            460.0
          ]
        }
      }
    ],
    "view_12": [
      {
        "tree_index": "7-0",
        "image_path": "/home/utkarsh/TreeInventorization/data/views/Bk0JN3NbFVnTKq3NYWgVFg_view12_tree0_box0.jpg",
        "confidence": 0.013235563412308693,
        "mask_data": {
          "orig_shape": [
            720,
            1024
          ],
          "encoding": "rle",
          "rle": {
            "size": [
              720,
              1024
            ],
            "counts": "fPd4k2ec00000008Hc0]O=C3M1O1O4L0006J7I6J=Co0QOg0YO;A?D=Ae\\\\a0"
          },
          "bbox": [
            210.0,
            374.0,
            231.0,
            513.0
          ]
        }
      }
    ]
  },
  "metadata": {
    "total_views": 6,
    "total_masks": 8
  }
}