{
  "pano_id": "bxlbmdckrQxJgw6ITUUHwg",
  "views": {
    "view_0": [
      {
        "tree_index": "0-0",
        "image_path": "/home/utkarsh/TreeInventorization/data/views/bxlbmdckrQxJgw6ITUUHwg_view0_tree0_box0.jpg",
        "confidence": 0.010657512582838535,
        "mask_data": {
          "orig_shape": [
            720,
            1024
          ],
          "encoding": "rle",
          "rle": {
            "size": [
              720,
              1024
            ],
            "counts": "Zk1f7j>000000O1O1O1O1002N1O1O4L5K5K0000000000000000dH`Bh5`=UJlBb5T=]JYCW5g<iJiCg4W<YKVDZ4j;fKcDm3];SLPE`3P;aL\\ER3d:nLdEj2\\:VMmEa2S:_MZFT2f9kMmF]1Y9cN\\Gf0f8ZO_G?c8A]G?c8A]G?c8A]G?YYbe0"
          },
          "bbox": [
            2.0,
            458.0,
            41.0,
            717.0
          ]
        }
      }
    ],
    "view_4": [
      {
        "tree_index": "1-0",
        "image_path": "/home/utkarsh/TreeInventorization/data/views/bxlbmdckrQxJgw6ITUUHwg_view4_tree0_box0.jpg",
        "confidence": 0.011164594441652298,
        "mask_data": {
          "orig_shape": [
            720,
            1024
          ],
          "encoding": "rle",
          "rle": {
            "size": [
              720,
              1024
            ],
            "counts": "fUR5_6Q`00000003M8Hi0WO6J001O0000000000000000000007I4L:F4L7I5K4L4L2N3M3M2N1O1O1O1O1O00001N100O1O10N10000001O01O010O01O002O1N2N2N2N101N2N2N2N4M1N1O100NMPKj^OP5Ta0TKi^Ol4Wa06K60ON2L4M3N3N001O10000O1O100O100001O0000O1N2NVMh_OAW`0>n_O_OR`0=T@Bj?:]@De?5a@Jb?Mf@1]?_OSA>P?SO^Ak0h>_NlA]1ha0K4kNh[OK[d0No[OLTd0OP\\OOQd01o[OOQd01o[OOQd01o[OOQbo>"
          },
          "bbox": [
            230.0,
            470.0,
            341.0,
            720.0
          ]
        }
      }
    ],
    "view_8": [
      {
        "tree_index": "2-0",
        "image_path": "/home/utkarsh/TreeInventorization/data/views/bxlbmdckrQxJgw6ITUUHwg_view8_tree0_box0.jpg",
        "confidence": 0.010177691467106342,
        "mask_data": {
          "orig_shape": [
            720,
            1024
          ],
          "encoding": "rle",
          "rle": {
            "size": [
              720,
              1024
            ],
            "counts": "fTQf0d2lc000000M3E;E;M3M3N2K5I7L4001O00O1O100O1O100n]O"
          },
          "bbox": [
            1002.0,
            578.0,
            1023.0,
            713.0
          ]
        }
      }
    ],
    "view_11": [
      {
        "tree_index": "3-0",
        "image_path": "/home/utkarsh/TreeInventorization/data/views/bxlbmdckrQxJgw6ITUUHwg_view11_tree0_box0.jpg",
        "confidence": 0.032541822642087936,
        "mask_data": {
          "orig_shape": [
            720,
            1024
          ],
          "encoding": "rle",
          "rle": {
            "size": [
              720,
              1024
            ],
            "counts": "jni?6_21Ua05^^O7]a0N[^O9aa0JZ^O:da0LT^O9ia0Om]O:la06_]O3]b06W]OOgb0P2M2N3M2N2N2N2N3M6J9G7I5K4L1O3l@eJbN3E4[=X5kC]LS<m3kBnLR=Z6N2N1O09G6J3M001O001O1O2N1O1O1O2N1O00O100O100O1O100O1O1N2O1O00L4L5J5K5K5L4N3N3M3M3N2M4jLl@jNW?Kn@_MF9h0R2g>LgBM^=LkBLZ=LoBH\\=WOfCa0Ya0Hj0POW]P5"
          },
          "bbox": [
            719.0,
            426.0,
            794.0,
            720.0
          ]
        }
      },
      {
        "tree_index": "4-0",
        "image_path": "/home/utkarsh/TreeInventorization/data/views/bxlbmdckrQxJgw6ITUUHwg_view11_tree0_box1.jpg",
        "confidence": 0.011401730589568615,
        "mask_data": {
          "orig_shape": [
            720,
            1024
          ],
          "encoding": "rle",
          "rle": {
            "size": [
              720,
              1024
            ],
            "counts": "g^]b0o2ac000000O2M3M3K5G9A>D<C=[Oe0ZOb0J7K30L3K1I:K9H:A?E;I9E;@a0\\Oc0E<E<[Og0VOk0^OgU\\3"
          },
          "bbox": [
            838.0,
            96.0,
            869.0,
            346.0
          ]
        }
      }
    ]
  },
  "metadata": {
    "total_views": 4,
    "total_masks": 5
  }
}