{
  "pano_id": "dRjuDT0lsGU4KPsKjnsWVg",
  "views": {
    "view_11": [
      {
        "tree_index": "0-0",
        "image_path": "/home/utkarsh/TreeInventorization/data/views/dRjuDT0lsGU4KPsKjnsWVg_view11_tree0_box0.jpg",
        "confidence": 0.011173478327691555,
        "mask_data": {
          "orig_shape": [
            720,
            1024
          ],
          "encoding": "rle",
          "rle": {
            "size": [
              720,
              1024
            ],
            "counts": "fYld0m2cc00000009G?A4L5K4L3M3M3M5K00000006J<Dl0TO?Am0SO<D8D7M000000ilo0"
          },
          "bbox": [
            950.0,
            342.0,
            977.0,
            485.0
          ]
        }
      }
    ]
  },
  "metadata": {
    "total_views": 1,
    "total_masks": 1
  }
}