{
  "pano_id": "eobW4Wr8HDNv196afsyiuQ",
  "views": {
    "view_0": [
      {
        "tree_index": "0-0",
        "image_path": "/home/utkarsh/TreeInventorization/data/views/eobW4Wr8HDNv196afsyiuQ_view0_tree0_box5.jpg",
        "confidence": 0.011446182616055012,
        "mask_data": {
          "orig_shape": [
            720,
            1024
          ],
          "encoding": "rle",
          "rle": {
            "size": [
              720,
              1024
            ],
            "counts": "Vek44\\f01O1O1O1O1O1O1O1O1O1O1O001O2N1O1O1O2N001O1O1O2N1O1O2N22N000O100O00001O0O2O00001O0000000O10O1000O10O1000O100001O0V[OF]c0;\\\\OMac07V\\O0hc0^1O1N101N10000001O1O2N1O2N2N00101O1O0O0bNQ\\O;oc0@W\\O?mc0WOZ\\Oi0hc0PO[\\OQ1bd0001O2N001O1m[OSOab0n0T]OEbb0<Y]OLcb06V]O1hb0n1g_OhLT=[3dBkL\\=U3_BPMa=Q3YBSMg=P3lAZMU>i2]AbMc>_2UAgMl>Z2n@iMT?\\2a@iMa?`2g_OmMY`0U40O01N2N2N101gNfIZB[6d=nIQBW6m=QJ`A[6_>l0O1N110O01O0oKUB^Ok=0RCEn<6aC_O_<?hC\\OX<`0RDYOo;b0ZDWOi;f0^DROf;l0_DoNb;Q1cDhN^;X1hDaN[;_1iD\\NW;e1mDVNT;j1REoMn:Q2i4O1O00O010QOdMm]O[2Ub0iMd]OX2^b0lMY]OV2jb0e03M3M3N2M3N2N2M3M3N2N2N2O1N2O1O1N2O1O1N2N2O1M3N2M3L4L4N2M3L4N2M3M3Ke0[O_oi="
          },
          "bbox": [
            221.0,
            278.0,
            394.0,
            608.0
          ]
        }
      }
    ],
    "view_3": [
      {
        "tree_index": "1-0",
        "image_path": "/home/utkarsh/TreeInventorization/data/views/eobW4Wr8HDNv196afsyiuQ_view3_tree0_box4.jpg",
        "confidence": 0.02060822583734989,
        "mask_data": {
          "orig_shape": [
            720,
            1024
          ],
          "encoding": "rle",
          "rle": {
            "size": [
              720,
              1024
            ],
            "counts": "`cd>\\1Te000000]OnNg[OV1Sd0oNi[Oa1fc0V1\\Ob0\\O>F9D=H4L1O2N1O2N04MO00eMZ_OlNf`0n0f_OmNZ`0n0S@hNn?S1f@^NZ?_1n@\\NR?b1TAZNm>c1XAYNi>d1^AVNd>h1S3N2M3M3M4M2N2M4M2N3M2M4L3O0O1O1O2N100O2N10M22O1N2O1O1N2O1O100000jWa6"
          },
          "bbox": [
            666.0,
            294.0,
            725.0,
            461.0
          ]
        }
      }
    ],
    "view_4": [
      {
        "tree_index": "2-0",
        "image_path": "/home/utkarsh/TreeInventorization/data/views/eobW4Wr8HDNv196afsyiuQ_view4_tree0_box8.jpg",
        "confidence": 0.010334792546927929,
        "mask_data": {
          "orig_shape": [
            720,
            1024
          ],
          "encoding": "rle",
          "rle": {
            "size": [
              720,
              1024
            ],
            "counts": "Rej55[f01O2N1O1O1O1O1O001O001O0000001O000000O1000000O10000000000O100O10000O10000002N1O1O1O1O2N1O2N1O2N2N1O1O2N1O1O1O2N1O1O2N1O1O1O2N3M3M2N7I5K4L2N2N3Z]O`NV`0b1Y_OJj?7m_O4P`00f_O7Y`0Q3O5KZJk_OQ5m`0M5K4L3M3M3M2N2N2N2N2N2N1O2N3M2N1ZMU^Oe0ma0TOf^O>[a0^OS_O7n`0EZ_O6f`0H__O5a`0Id_O4[`0Ji_O5W`0Jm_OOV`01n_OJS`06S@Cn?=R31O001N2O1O1O1O100O1O1O10O010O10O10O0JdZOZO\\e0e0fZOYO[e0b0;01M201O01O00O1100O0000001O01O0O1000O1000O10O2O0O011N101000000jmV="
          },
          "bbox": [
            265.0,
            338.0,
            421.0,
            529.0
          ]
        }
      }
    ],
    "view_12": [
      {
        "tree_index": "3-0",
        "image_path": "/home/utkarsh/TreeInventorization/data/views/eobW4Wr8HDNv196afsyiuQ_view12_tree0_box0.jpg",
        "confidence": 0.028220854699611664,
        "mask_data": {
          "orig_shape": [
            720,
            1024
          ],
          "encoding": "rle",
          "rle": {
            "size": [
              720,
              1024
            ],
            "counts": "WaV>W4Yb000000ZOf0H8L4M3H800000000000000000_Lf_Ol0Z`0mNZ@f0f?UOo@;Q?BlADT>8ZBZOfb0FnUi7"
          },
          "bbox": [
            646.0,
            282.0,
            668.0,
            461.0
          ]
        }
      },
      {
        "tree_index": "4-0",
        "image_path": "/home/utkarsh/TreeInventorization/data/views/eobW4Wr8HDNv196afsyiuQ_view12_tree0_box1.jpg",
        "confidence": 0.02358502522110939,
        "mask_data": {
          "orig_shape": [
            720,
            1024
          ],
          "encoding": "rle",
          "rle": {
            "size": [
              720,
              1024
            ],
            "counts": "Z[e`0j1fd000000O2L6J6J6I6G<^\\OZMUb0MS^Oa3ka0c0O1O4L00000000]MW^O?ia0\\OS_OMm`01[_OIe`05a_OCc`0:d_O@^`06n_OGZ`0AZ@:Sc0GiYX5"
          },
          "bbox": [
            758.0,
            346.0,
            783.0,
            489.0
          ]
        }
      }
    ]
  },
  "metadata": {
    "total_views": 4,
    "total_masks": 5
  }
}