{
  "pano_id": "Gv1ztqDtIXSW4Qg9_ul5_Q",
  "views": {
    "view_0": [
      {
        "tree_index": "0-0",
        "image_path": "/home/utkarsh/TreeInventorization/data/views/Gv1ztqDtIXSW4Qg9_ul5_Q_view0_tree0_box3.jpg",
        "confidence": 0.010115675628185272,
        "mask_data": {
          "orig_shape": [
            720,
            1024
          ],
          "encoding": "rle",
          "rle": {
            "size": [
              720,
              1024
            ],
            "counts": "RVd9`0Pf00000001O2N2N3M6J5K4L5K3M3M3M27I5KO2N1O4\\[OPO_c0Z2Ga0_O4L2N1N4M3L3M4L4L5K3M3M3N2M2N2N2N2N2O0O2O1N11UKk^Oo03e1Qb0fM]^OU2ha0^Mc^O_2jb0N5_MQ]OU1[d0K5K4L1N1001O0O102M3M3M1O3M5K4K3N2N1O1OO101N2N2N3M5K6J1N3N4K6K2M2N2N2N2M]So:"
          },
          "bbox": [
            438.0,
            226.0,
            523.0,
            482.0
          ]
        }
      }
    ],
    "view_11": [
      {
        "tree_index": "1-0",
        "image_path": "/home/utkarsh/TreeInventorization/data/views/Gv1ztqDtIXSW4Qg9_ul5_Q_view11_tree0_box1.jpg",
        "confidence": 0.010211869142949581,
        "mask_data": {
          "orig_shape": [
            720,
            1024
          ],
          "encoding": "rle",
          "rle": {
            "size": [
              720,
              1024
            ],
            "counts": "nbb0`4Pb0000000000000000000000000000000000?Aa0`LU_O9cc0N000000Z]\\e0"
          },
          "bbox": [
            26.0,
            318.0,
            49.0,
            461.0
          ]
        }
      }
    ]
  },
  "metadata": {
    "total_views": 2,
    "total_masks": 2
  }
}