{
  "pano_id": "h-UexjsOv41-sc6kkp1IVg",
  "views": {
    "view_0": [
      {
        "tree_index": "0-0",
        "image_path": "/home/utkarsh/TreeInventorization/data/views/h-UexjsOv41-sc6kkp1IVg_view0_tree0_box0.jpg",
        "confidence": 0.026965200901031494,
        "mask_data": {
          "orig_shape": [
            720,
            1024
          ],
          "encoding": "rle",
          "rle": {
            "size": [
              720,
              1024
            ],
            "counts": "Xdd>X1Xe000000O8Da0@f4ZKi4XK7G6K5K4M3N2M3L4L4L4H8000000000O1kDPGi8Q9oF^If6f6TI^;L4L4K5K5M3K5K5M3M3LV]Q7"
          },
          "bbox": [
            666.0,
            302.0,
            702.0,
            720.0
          ]
        }
      },
      {
        "tree_index": "1-0",
        "image_path": "/home/utkarsh/TreeInventorization/data/views/h-UexjsOv41-sc6kkp1IVg_view0_tree0_box5.jpg",
        "confidence": 0.012099890038371086,
        "mask_data": {
          "orig_shape": [
            720,
            1024
          ],
          "encoding": "rle",
          "rle": {
            "size": [
              720,
              1024
            ],
            "counts": "ZRZ8b2nc00000005Kc0]Ol0j^OeL_=g6@;Df0_AjG]=U9_O>CR1nNc0^O<C:G5O12G;E8H8H9G9Gc0]O`3`Lh1XN`0@=C9Gb0^Og0YO9Gb0XOe0lNhZOHoc]="
          },
          "bbox": [
            378.0,
            298.0,
            412.0,
            713.0
          ]
        }
      },
      {
        "tree_index": "2-0",
        "image_path": "/home/utkarsh/TreeInventorization/data/views/h-UexjsOv41-sc6kkp1IVg_view0_tree0_box8.jpg",
        "confidence": 0.010415581054985523,
        "mask_data": {
          "orig_shape": [
            720,
            1024
          ],
          "encoding": "rle",
          "rle": {
            "size": [
              720,
              1024
            ],
            "counts": "gni1d0le000000100001O2M2O1O1N3OO01O1O1O1O1O2M20000O2O2N4LP1oNh0g\\OjNCdNS?T7ZO5K4Kf1[Nh0WO8I5K8H6JN2N2N1O2N3M3M2N4L<Dm0TFgCS4_OjNT`0hMRB^1ma0Ch1XNQ`bc0"
          },
          "bbox": [
            82.0,
            311.0,
            131.0,
            713.0
          ]
        }
      }
    ]
  },
  "metadata": {
    "total_views": 1,
    "total_masks": 3
  }
}