{
  "pano_id": "hielIS2C9RlG1noIvThWrg",
  "views": {
    "view_0": [
      {
        "tree_index": "0-0",
        "image_path": "/home/utkarsh/TreeInventorization/data/views/hielIS2C9RlG1noIvThWrg_view0_tree0_box0.jpg",
        "confidence": 0.029183294624090195,
        "mask_data": {
          "orig_shape": [
            720,
            1024
          ],
          "encoding": "rle",
          "rle": {
            "size": [
              720,
              1024
            ],
            "counts": "g\\P9Z1Ve000000O2L3M7F6iNW1K5K5L013N1N3L4N2N2N1N3N2N2N2M3M3O1M3M3N2O1O0O2K41O1O1N2M3J6nNR1G9_Oa0oMV\\Og0_d0UOh[Oc0bd0UOc[Od0cd0ZO^[Od0dd0\\O\\[Od0dd0\\O\\[Od0dd0\\O\\[Od0\\c^<"
          },
          "bbox": [
            410.0,
            2.0,
            457.0,
            165.0
          ]
        }
      }
    ],
    "view_12": [
      {
        "tree_index": "1-0",
        "image_path": "/home/utkarsh/TreeInventorization/data/views/hielIS2C9RlG1noIvThWrg_view12_tree0_box1.jpg",
        "confidence": 0.014637669548392296,
        "mask_data": {
          "orig_shape": [
            720,
            1024
          ],
          "encoding": "rle",
          "rle": {
            "size": [
              720,
              1024
            ],
            "counts": "jgV>j0k1\\Oja0d0V^O\\Oja0d0V^O\\Oja0d0V^O\\Ofa0l0l]OHaa0i2C=kMU2I7]OjId@\\6X?`0N3N10000O10001O00000001O000O2kKh@P1Y?lNl@Q1V?lNn@\\Og0ZN_>n1WARNSb0>a[d7"
          },
          "bbox": [
            646.0,
            413.0,
            675.0,
            644.0
          ]
        }
      },
      {
        "tree_index": "2-0",
        "image_path": "/home/utkarsh/TreeInventorization/data/views/hielIS2C9RlG1noIvThWrg_view12_tree0_box5.jpg",
        "confidence": 0.01184675469994545,
        "mask_data": {
          "orig_shape": [
            720,
            1024
          ],
          "encoding": "rle",
          "rle": {
            "size": [
              720,
              1024
            ],
            "counts": "X]jc0m0ce0000001O20O10O01O01O0001O001O1O001O10O01O01O00000001N10000O2O1N101O1N2O10O10100O2N2O01O00001N4L1N2N2O1N2O001N3N1N3N3L4i[OcNRc0g2G3M3M3R@eLTMGU?f3bCRMX<P3eCSMX<Q3eCQMY<R3cCQMY<T3dCnLW<W3fCkLR<`3jC`LY:LRDR4`1RLT:P6gERJb9g6ZFZI]9U7[FnH]9d7VF_Hi9^3WEB<UM\\:W3[Ei1c:VN_Ek1_:SNiEh1V:WNoEg1o9XNSFi1k9VNVFk1i9SNZFn1d9PN_FQ2_9nMbFT2\\9kMfFV2X9oJUFg0d0WNoNO<c4j9ZLcFg09[N1b4R9ZKlGc1QOaN4b4c;eLZDgN7c4b;aLWDkN:e4_;]LWDmN=e4];\\LWDlN`0i4X;YLYDkNb0m4T;XLZFh3e9WL\\Fj3c9UL_Fk3`9UL`Fl3_9SLcFP4Y9oKhFP4Y9PLgCPO\\2o4n9QLcCTO_2i4P:RLZC^Od2_4S:lLkES3U:oLjEP3W:PMiEo2W:RMhEn2Y:QMhEn2X:SMgEm2Z:RMgEm2Z:RMfEn2Z:RMfEn2Y:SMgEm2Y:RMiEm2W:SMiEm2U:UMkEk2T:WMjEj2S:YMmEg2n9_MPFb2n9aMQF_2o9aMQF_2e1"
          },
          "bbox": [
            902.0,
            166.0,
            1023.0,
            585.0
          ]
        }
      }
    ]
  },
  "metadata": {
    "total_views": 2,
    "total_masks": 3
  }
}