{
  "pano_id": "I8AjaXBgOaxp3osyxffVpQ",
  "views": {
    "view_12": [
      {
        "tree_index": "0-0",
        "image_path": "/home/utkarsh/TreeInventorization/data/views/I8AjaXBgOaxp3osyxffVpQ_view12_tree0_box0.jpg",
        "confidence": 0.0447845458984375,
        "mask_data": {
          "orig_shape": [
            720,
            1024
          ],
          "encoding": "rle",
          "rle": {
            "size": [
              720,
              1024
            ],
            "counts": "jZ[d0\\1Te00000007IZ1fNg0YO6J4L4L5K;Ef0ZO2N2n_OeJQO2b?Z5[AoJc>R5\\AoJc>S5ZAoJe>S5YAmJg>U5WAlJh>V5UAkJk>V5TAkJk>V5TAjJl>W5TAhJl>Z5QAhJn>_5g@fJX?Y601O00001O000000001O000000TI]Ak5f?N0001O0N3K4M4L4N5K10000O10000001O00000XLo@MV?]M\\@i1n1Ai=cNb@X1g2^Oi<WOo@5XOKb3`0Ub0Fk^g0"
          },
          "bbox": [
            926.0,
            250.0,
            989.0,
            485.0
          ]
        }
      }
    ]
  },
  "metadata": {
    "total_views": 1,
    "total_masks": 1
  }
}