{
  "pano_id": "iWJp5acPsBKXZ3vTu7sKWg",
  "views": {
    "view_1": [
      {
        "tree_index": "0-0",
        "image_path": "/home/utkarsh/TreeInventorization/data/views/iWJp5acPsBKXZ3vTu7sKWg_view1_tree0_box2.jpg",
        "confidence": 0.026864266023039818,
        "mask_data": {
          "orig_shape": [
            720,
            1024
          ],
          "encoding": "rle",
          "rle": {
            "size": [
              720,
              1024
            ],
            "counts": "iRZ8:Vf000000010001O1O0001O01O00001O2O00011M2N100O2N1O0010O10O000O1O2M2J7K4M4O1O1O3M8I2OO8HO01O01O000O2N3fMiNU_OZ1U`0^NV^OR1T1c0o4XNZ5a1eE:h4[Nc5\\1cE`0^4ZNo5V1bEg0P4\\N^6n0`El0e3^Nk6j0ZER1_3XNW7l0PE]1Z3iMf7n4RHTKn7P5mGQKS8S5hGnJX8U5cGmJ]8V5_GkJa8X5[GiJe8Y5XGhJh8[5SGgJm8\\5oF_JW9d5dF[J_9i5_E]IROl0_;X91000000mHfDo2[;lKbDdMl0\\6c:SKlFf4X9TKPGj4P9nJZGo4R9XJ]Gg5h<M3N2M4M2N2M4L3aNP_OZMRa0b2R_O[MPa0b2S_O\\MPa0e0`_OVOE1o`0c0e_OUO_O6n`0b0h_OSO^O7o`0b0g_OQO_O7o`0g0o@QOW?m0W3O1O000000R_o;"
          },
          "bbox": [
            378.0,
            270.0,
            477.0,
            621.0
          ]
        }
      }
    ],
    "view_11": [
      {
        "tree_index": "1-0",
        "image_path": "/home/utkarsh/TreeInventorization/data/views/iWJp5acPsBKXZ3vTu7sKWg_view11_tree0_box6.jpg",
        "confidence": 0.017344273626804352,
        "mask_data": {
          "orig_shape": [
            720,
            1024
          ],
          "encoding": "rle",
          "rle": {
            "size": [
              720,
              1024
            ],
            "counts": "bUV97Yf00000001O4L2N2N1O2N2N1O2N2N2N1O1O2N2N1O2N2N3M31NO1O4L4L4L5K4L4K4M7H5L2N1N2O1N3N0O101N2N2N1O3M3_]OWMTa0l2c^O_MXa0c2e^O_M[a0c2a^O_M^a0k3N1O1O001O1MULl^O`2n`0cMY_OY2g`0dMb_OV2^`0iMg_OT2X`0iMo_OS2Q`0kMT@R2l?lMY@Q2g?nM\\@i1k?UNZ@P1cNbNUa0<\\@o0cN^N^a06U@S1Sc0J5N3N1O11O2N1O10001N3M2N1O3M4L2N102M2N2O002005J5I3O00000O2N4NO001N11O0O2N10O100N101O000010001N3NO0101O1N12N12L1OO2O1O1N3N3K5K3N1N4K5J7J6H_WY:"
          },
          "bbox": [
            418.0,
            274.0,
            554.0,
            564.0
          ]
        }
      }
    ],
    "view_12": [
      {
        "tree_index": "2-0",
        "image_path": "/home/utkarsh/TreeInventorization/data/views/iWJp5acPsBKXZ3vTu7sKWg_view12_tree0_box0.jpg",
        "confidence": 0.020784759894013405,
        "mask_data": {
          "orig_shape": [
            720,
            1024
          ],
          "encoding": "rle",
          "rle": {
            "size": [
              720,
              1024
            ],
            "counts": "ncYa04\\f03M3W[OKh5d0X5CnDKd5m0fI_OV:K^FJa5^2n3jM`FHgNO^6d2Y4iM^FNU5]2\\4gM\\F1P5\\2d4eMXFY3g1WOQ8cMTFi3S1jNi8aMnER4h0bN[9^MiEX4`0`Ng9_M]E_4:YN[:d71O1N2N2M3M3L4G9ZO_DQFm;`9i0K5L;G6I5K6YH_B:H`4n=PKdB]OR2h3_;gLdFQ2`9lMfFm1\\9SNhFk0^KdNU>?bFe0W:[OlE?W:@mE:U:EPF5R:KSFMP:4U60000O011O01O01N111M2O1N3N100000Vfo3"
          },
          "bbox": [
            787.0,
            270.0,
            841.0,
            645.0
          ]
        }
      },
      {
        "tree_index": "3-0",
        "image_path": "/home/utkarsh/TreeInventorization/data/views/iWJp5acPsBKXZ3vTu7sKWg_view12_tree0_box4.jpg",
        "confidence": 0.010326525196433067,
        "mask_data": {
          "orig_shape": [
            720,
            1024
          ],
          "encoding": "rle",
          "rle": {
            "size": [
              720,
              1024
            ],
            "counts": "j`\\;S2]d00000003M8H8H5K3M2N3M3M1O2N2N3M2N2N3M3M1O2N3M2N2N3M2N3M2N3M5K`0@3M2N2N24K3M0000O2O0O2O1N2O2N2N1O2M3N3L4M2N2M6K3M2N2N4K5L2M5L6I7J3L5L4K3N2N2M4M3L3N1O00001O2N4]BfGf<V9M00O100O010O100O00iNkFTET9k:SGoDm8l:ZGSEk3WO9j;jKmDi3_O;f;kKjDc3JiM@g0m;mMiD[33hMEh0b;TNeDV3<]M=h0d:dNbD_2X1lMLl0]:gN_DV2f1oMER1X:hN[Do1e4XOQ7hNZDk1l4[Ol6hNWDk1Q5[Ol6gNRDh1Z5_Of6hNoCb1c5E`6iNjC_1l5E\\6mNfC[1S6DZ6TO]CT1b6CS6f0XJTOj5h0`JoNc5n0eJgN`5W1m7M3O1O00N1O200L42N2N2O1M3N2N2O1M3N2N2N2M3K5K5M3MYXU8"
          },
          "bbox": [
            518.0,
            314.0,
            651.0,
            655.0
          ]
        }
      }
    ]
  },
  "metadata": {
    "total_views": 3,
    "total_masks": 4
  }
}