{
  "pano_id": "jofuP7tNAfVyFwsKsgDb8A",
  "views": {
    "view_8": [
      {
        "tree_index": "0-0",
        "image_path": "/home/utkarsh/TreeInventorization/data/views/jofuP7tNAfVyFwsKsgDb8A_view8_tree0_box0.jpg",
        "confidence": 0.03414153680205345,
        "mask_data": {
          "orig_shape": [
            720,
            1024
          ],
          "encoding": "rle",
          "rle": {
            "size": [
              720,
              1024
            ],
            "counts": "Rim8>Rf00000002N4L5K3M:F7I4L4L4La1_N5K5K5K00O7J4K4M3L3N2N2M3N2N3M2N1O2N1O1O10O0100O102N1N102N3L2O00001O00010O01c0\\O110O000010N3N1V\\OYOfa0k0j]ODSb0`2N1M3O0O10O001O03NN1O2N3M2N3M2N2N2N3M2N3M5K6J6J;Ea1_N5K2N1O2N2N1O000000h_^;"
          },
          "bbox": [
            406.0,
            322.0,
            501.0,
            565.0
          ]
        }
      }
    ],
    "view_11": [
      {
        "tree_index": "1-0",
        "image_path": "/home/utkarsh/TreeInventorization/data/views/jofuP7tNAfVyFwsKsgDb8A_view11_tree0_box1.jpg",
        "confidence": 0.014579234644770622,
        "mask_data": {
          "orig_shape": [
            720,
            1024
          ],
          "encoding": "rle",
          "rle": {
            "size": [
              720,
              1024
            ],
            "counts": "Rnb:Y7n6PJ2P6NPJ2P6NPJ2P6NPJ2Q6KQJ5R6DRJ<P6]OUJc0m5SO[Jm0g5iNaJW1a5bNdJ^1^5\\NfJd1\\5WNgJi1Z5RNjJn1W5oMkJQ2W5hMnJX2T5[MWKe2k4oL_KQ3b4fLfKZ3]4SLSLm3o3kKWLU4k3fKXLZ4i3bKZL^4i3ZK\\Lf4f3RK`Ln4a3kJeLU5]3dJhL\\5Z3]JkLc5X3WJkLi5X3QJkLo5Y3kIiLU6]3aIgL_6e90000000000000^ChJl7X5mGZKh7f4kGlKP8T4TGmLg8S3kF_MQ9a2iFgMU9Y2eFoMY9Q2_FZN^9^7N2N2N2N2N3M2B?G8C>H7C?_O`0H7K5J6F:B>F9G:E;I6K5K6H7I8K4K5L4L3M4M3L4L3N3M3L5K4M3L5J6J6L3M4L4L3N2N3L3N2N2N2N1N3N10000000bec9"
          },
          "bbox": [
            482.0,
            34.0,
            585.0,
            529.0
          ]
        }
      }
    ],
    "view_12": [
      {
        "tree_index": "2-0",
        "image_path": "/home/utkarsh/TreeInventorization/data/views/jofuP7tNAfVyFwsKsgDb8A_view12_tree0_box0.jpg",
        "confidence": 0.030172383412718773,
        "mask_data": {
          "orig_shape": [
            720,
            1024
          ],
          "encoding": "rle",
          "rle": {
            "size": [
              720,
              1024
            ],
            "counts": "\\oSc0j1fd000000N2M3M3M3M3M3K5L4K5H8J6M3M3M3L4K5L4K5K5M3M3M3K5L4_N]KQAg4i>bKo@^4P?jKi@Z4S?mKg@V4W?oKc@S4\\?`1M1O2N1O00O21O10N0O11O1O00O30000M21O0O2N1M34M3L4K5H8L4J6K5L4L4M3L4K5M3L4UNT_OmMQa0j1\\_OkMk`0P2__OdMh`0X2j1J6J6K5L4J6K5L4L4L4J6L4J6E;M3N2N\\f]1"
          },
          "bbox": [
            870.0,
            6.0,
            958.0,
            325.0
          ]
        }
      }
    ]
  },
  "metadata": {
    "total_views": 3,
    "total_masks": 3
  }
}