{
  "pano_id": "RbyqAY32YcQiZh6HQbdc5w",
  "views": {
    "view_0": [
      {
        "tree_index": "0-0",
        "image_path": "/home/utkarsh/TreeInventorization/data/views/RbyqAY32YcQiZh6HQbdc5w_view0_tree0_box7.jpg",
        "confidence": 0.0144797433167696,
        "mask_data": {
          "orig_shape": [
            720,
            1024
          ],
          "encoding": "rle",
          "rle": {
            "size": [
              720,
              1024
            ],
            "counts": "SmQe08Xf00000001O1O2N1O1O1O100O1O101N100000001N101N2N2N3N1N3M2M3J6L5L4L3M4M5J7J4K5L9G7H6G:J7Ia0_O7I3M3M3M2N1O2N1O00000000dKm^O[3Sa0bLR_OZ3Pa0cLU_OY3m`0fLW_OU3k`0jLV_OV3j`0jLV_OW3i`0iLU_OY3k`0gLS_O\\3l`0dLS_O^3l`0bLT_O^3R7"
          },
          "bbox": [
            958.0,
            314.0,
            1023.0,
            473.0
          ]
        }
      }
    ],
    "view_4": [
      {
        "tree_index": "1-0",
        "image_path": "/home/utkarsh/TreeInventorization/data/views/RbyqAY32YcQiZh6HQbdc5w_view4_tree0_box4.jpg",
        "confidence": 0.017091261222958565,
        "mask_data": {
          "orig_shape": [
            720,
            1024
          ],
          "encoding": "rle",
          "rle": {
            "size": [
              720,
              1024
            ],
            "counts": "Q_h5<a2h2n=XMRBh2n=XMRBh2n=XMRBh2l=\\Mj@l3S?\\L[@Q4b?`1N2J6ZOf0D<E;J60000000000000000000K5^Ob0B>dN\\1^Nb1F:XMe]Ob01cN`b0k0_]Ob01cN`b0k0_]Ob01cN`b0k0_]Ob01cNbeQ`0"
          },
          "bbox": [
            262.0,
            190.0,
            293.0,
            449.0
          ]
        }
      },
      {
        "tree_index": "2-0",
        "image_path": "/home/utkarsh/TreeInventorization/data/views/RbyqAY32YcQiZh6HQbdc5w_view4_tree0_box8.jpg",
        "confidence": 0.013500943779945374,
        "mask_data": {
          "orig_shape": [
            720,
            1024
          ],
          "encoding": "rle",
          "rle": {
            "size": [
              720,
              1024
            ],
            "counts": "jfl9>Rf0000000002N3M1O2N3M4`ZO@hd0Z1Ja0_O:_^OgMW>]2YARNd>P2k@`NT?b1b@gN]?Z1S@VOl?m0__OI]`0U300000000009G1O2N2N2N2N2N5K5K3M2N2N2N2N1K400O100O10O0001jNV^OeMja0Y2^^OaMba0]2c^O`M]a0_2i^O[MXa0c2n^OXMSa0g2[1N2N2N100N2L4M3M4F:M3O1N200O1]Oc[OSO_d0i0f[OTO[d0k0h[OSOXd0l0j[OSOVd0l0l[OROUd0n0k[OUORd0j0o[O[Olc0e0S\\O_Ojc0`0W\\OBgc0>Z\\OBec0>[\\OCdc0=[\\OEdc0;\\\\OF`c0=`\\OCac0<_\\ODbc0:^\\OHbc07^\\OIcc06^\\OIcc06]\\OKcc04]\\OLdc03\\\\OMec02[\\ONfc01Z\\O0fc0N[\\O2fc0MZ\\O3gc0LZ\\O4fc0KZ\\O5gc0JY\\O6hc0IY\\O7gc0HY\\O8hc0GX\\O9ic0FW\\O9kc0EV\\O:lc0EU\\O:lc0ET\\O;mc0DS\\O;oc0DQ\\O<Pd0CP\\O=Qd0Bo[O>Rd0Am[O`0Qe00O1VOKY[O6hd0h01O1O1O1O1O100O1O1O1O1O1O1O1O1N2N2M3L4N2N2O1N2N2M3N2O1NXXb9"
          },
          "bbox": [
            450.0,
            314.0,
            587.0,
            501.0
          ]
        }
      }
    ],
    "view_9": [
      {
        "tree_index": "3-0",
        "image_path": "/home/utkarsh/TreeInventorization/data/views/RbyqAY32YcQiZh6HQbdc5w_view9_tree0_box0.jpg",
        "confidence": 0.0218659695237875,
        "mask_data": {
          "orig_shape": [
            720,
            1024
          ],
          "encoding": "rle",
          "rle": {
            "size": [
              720,
              1024
            ],
            "counts": "Wja<4Zf05L3M2N3M3N1N2N3M3J6N1O2N1O2N1O1O1O2N1O43M4J3M03M1N000O2N2X^OcNY>_1YAQOc>R1o@ZOP?j0\\@Fd?=o_ONP`06e_O5X`0O]_O7d`0j21O2N2N2N3M5K6J1O1O1O1O00O10000000000N\\NT_OhMg`0T2c_OkMV?KR@W2P1nMh>5Q@l1[1oMd>;h_Og1i1kM_>V3^2N2N2O1N2N2N2QOh\\OdNZc0T1[]O[Nib0^1X1J;K1O1O1N2O0O2N1N5K8GVWU8"
          },
          "bbox": [
            571.0,
            330.0,
            651.0,
            521.0
          ]
        }
      }
    ]
  },
  "metadata": {
    "total_views": 3,
    "total_masks": 4
  }
}