{
  "pano_id": "rFOKfrMeMcDR5dyOMROZKg",
  "views": {
    "view_1": [
      {
        "tree_index": "0-0",
        "image_path": "/home/utkarsh/TreeInventorization/data/views/rFOKfrMeMcDR5dyOMROZKg_view1_tree0_box0.jpg",
        "confidence": 0.013433219864964485,
        "mask_data": {
          "orig_shape": [
            720,
            1024
          ],
          "encoding": "rle",
          "rle": {
            "size": [
              720,
              1024
            ],
            "counts": "^Wj6d0n2R1Z>nNfAR1Z>nNfAR1Z>nNfAR1Y>oNbAZ1Z>gN[Ai1_>XNUA[2c>hMo@i2j>[Ml@l2T?YM_@o2`?XMj_OX3T`0c1O11O001O5K6J3M2N2N3M3M2N3M4L;E=C2N2N2N2N1O1O1O1O2G9cN_1YN\\Zj>"
          },
          "bbox": [
            310.0,
            264.0,
            348.0,
            461.0
          ]
        }
      }
    ],
    "view_3": [
      {
        "tree_index": "1-0",
        "image_path": "/home/utkarsh/TreeInventorization/data/views/rFOKfrMeMcDR5dyOMROZKg_view3_tree0_box0.jpg",
        "confidence": 0.013175365515053272,
        "mask_data": {
          "orig_shape": [
            720,
            1024
          ],
          "encoding": "rle",
          "rle": {
            "size": [
              720,
              1024
            ],
            "counts": "hlR3l1db0UO_]Oo1Pb0_1mMcKmAa4P>cKjAa4U>`KgAe4V>]KgAe4Y>]KcAf4\\>[K`Ah4`>YK\\Ak4c>WKWAn4g>VKRAR5j>Z1000000000000000000000000001O001O001O2N2N3M5K4L4L2N2N2N3H8K=Bg0eMV^O^Mgj^b0"
          },
          "bbox": [
            140.0,
            331.0,
            183.0,
            553.0
          ]
        }
      }
    ],
    "view_12": [
      {
        "tree_index": "2-0",
        "image_path": "/home/utkarsh/TreeInventorization/data/views/rFOKfrMeMcDR5dyOMROZKg_view12_tree0_box0.jpg",
        "confidence": 0.010603934526443481,
        "mask_data": {
          "orig_shape": [
            720,
            1024
          ],
          "encoding": "rle",
          "rle": {
            "size": [
              720,
              1024
            ],
            "counts": "nZ\\c0Z8V>000000000000000000O100^OnAeHS>Z7PBcHQ>\\7b000N2M3N2N2M3O100O1oHn@d6d?K4M2M2N2000O001N6J8I4J7J7I2M4M1N2O1N3N1N3N4hAbHU=o8]O4L4L3M5K4L5KjH[Dm3Z;oKVEk3d:SLQF_3h9aLeFY3T9fLWGV3a8lLjGS3g7SM`Hh2`7UMgHg2Y7WMmHe2S7YMRId2n6ZMVI7aLTOY:c0YI3hLUOo9e0]I2lLTOg9i0^I1QMROa9k0aI2QMPO^9l0cI4SMlNZ9m0fI7XMdNR9T1gI8^M]Nk8Z1iI9cMUNd8`1kI;RNdMS8o1mI=i8BYG>f8@]G?c8_O_Ga0a8\\OdGc0[8ZOjGd0V8YOoGe0Q8WOTHg0X8kNmGS1U8hNQHU1o7jNUHR1k7mNZHn0g7RO_Hf0d7YO\\IFe6:`I_Oc6`0dIUO`6k0c7O10000000iTP1"
          },
          "bbox": [
            882.0,
            190.0,
            977.0,
            577.0
          ]
        }
      }
    ]
  },
  "metadata": {
    "total_views": 3,
    "total_masks": 3
  }
}