{
  "pano_id": "sJTKb8_jB4vTNiMeUtEmFA",
  "views": {
    "view_0": [
      {
        "tree_index": "0-0",
        "image_path": "/home/utkarsh/TreeInventorization/data/views/sJTKb8_jB4vTNiMeUtEmFA_view0_tree0_box0.jpg",
        "confidence": 0.031513508409261703,
        "mask_data": {
          "orig_shape": [
            720,
            1024
          ],
          "encoding": "rle",
          "rle": {
            "size": [
              720,
              1024
            ],
            "counts": "VU\\6=Sf00000001O2N2N2N1O14L1O010O010O001O2N1OO1O1O100O2N1O1O1O2N1O2N2N2L5H9K4N3M5M2L3k[ObNPc0c2L3M2N2L4L7I7H9Gd0\\Og0WOa0D6J6JWKW@k2i?QM`@j2`?RMo@c2Q?[MUAa2k>^MXA`2h>^M]A_2c>_MbA^2^>`MdA`2\\>_McAc2]>[MdAf2\\>YMdAh2\\>VMfAj2Z>TMhAl2X>QMlAn2T>PMnAP3X>hLkA9UNO3m0o?gNlA7ZNN5n0g?gNoA9Di0n`0TO[_Oe0]c0K4L8Bam^>"
          },
          "bbox": [
            290.0,
            262.0,
            364.0,
            465.0
          ]
        }
      }
    ]
  },
  "metadata": {
    "total_views": 1,
    "total_masks": 1
  }
}