{
  "pano_id": "sYtn_I1t9YjHvONbMdcb0w",
  "views": {
    "view_0": [
      {
        "tree_index": "0-0",
        "image_path": "/home/utkarsh/TreeInventorization/data/views/sYtn_I1t9YjHvONbMdcb0w_view0_tree0_box1.jpg",
        "confidence": 0.0313451774418354,
        "mask_data": {
          "orig_shape": [
            720,
            1024
          ],
          "encoding": "rle",
          "rle": {
            "size": [
              720,
              1024
            ],
            "counts": "bjW29a6j2R6VMnIj2R6VMnIj2R6VMnIj2R6WMlIo2^KnL]84TL[3lJmLj8JWLY5g3iJWLY5g3lJSLW5k3QKjKT5T4QKeKV5V4mJcK^5V4eJcJb6Z5bIcI_7[6gHSIh7j6YInGo6Q8bISGk6k8]305K000000000000000000000000jBYGc<g8ZC^Gd<b8YCaGg<U9O1O0000O10000O100O1000[GoFk3P9gKRH@iN:Z9[OjIQOiMn0^8F[JlNgMV1n7B`N0`1VOC??[O0YOhFNZ9d0a;K5M3N2O1N2O1O10000000lTkb0"
          },
          "bbox": [
            102.0,
            114.0,
            165.0,
            545.0
          ]
        }
      },
      {
        "tree_index": "1-0",
        "image_path": "/home/utkarsh/TreeInventorization/data/views/sYtn_I1t9YjHvONbMdcb0w_view0_tree0_box3.jpg",
        "confidence": 0.017900042235851288,
        "mask_data": {
          "orig_shape": [
            720,
            1024
          ],
          "encoding": "rle",
          "rle": {
            "size": [
              720,
              1024
            ],
            "counts": "]cP9f1Q5C[KTO[=Y1ZGC[KTO[=Y1ZGC[KTO[=Y1ZGC[KTOZ=g1iF5R98fEi0U:3fD;U;b5N2N2M2O2N5K1O100O100O1OTG^Cl7b<PHdCn7\\<PHgCo7Y<PHhCP8X<nGjCR8V<lGlCT8S<kGoCU8Q<iGQDW8o;gGRDZ8n;eGSD[8l;dGVD\\8j;cGWD]8i;bGXD^8g;bGZD^8e;`G^D`8^;bGeD]8[;bGgDJZOR8o;SH\\Ej7d:VH^Eh7b:WHaE^7h:aHZEU5aNUK]=EUDe4[=ZKgB]2SOmMSa0i1Q2H8POn[OXOVd0h0j[OXOVd0h0j[OXOVd0h0j[OXOSW^<"
          },
          "bbox": [
            410.0,
            306.0,
            457.0,
            629.0
          ]
        }
      },
      {
        "tree_index": "2-0",
        "image_path": "/home/utkarsh/TreeInventorization/data/views/sYtn_I1t9YjHvONbMdcb0w_view0_tree0_box5.jpg",
        "confidence": 0.012560677714645863,
        "mask_data": {
          "orig_shape": [
            720,
            1024
          ],
          "encoding": "rle",
          "rle": {
            "size": [
              720,
              1024
            ],
            "counts": "lTY>X2Xd000000M4eNZ1E<K5L3N2N2M3M2N3M3N2O001O10O01000O1000O1000000O10001O01O1O2N4fK`^O[3Yc0POg1VNk\\[7"
          },
          "bbox": [
            650.0,
            37.0,
            688.0,
            198.0
          ]
        }
      }
    ],
    "view_6": [
      {
        "tree_index": "3-0",
        "image_path": "/home/utkarsh/TreeInventorization/data/views/sYtn_I1t9YjHvONbMdcb0w_view6_tree0_box4.jpg",
        "confidence": 0.016025718301534653,
        "mask_data": {
          "orig_shape": [
            720,
            1024
          ],
          "encoding": "rle",
          "rle": {
            "size": [
              720,
              1024
            ],
            "counts": "R_Q`06Zf0000000001O1O1O1O1O2N1O1O1O1O1O1O002N1O2N3Me0[O2N2N2N2N2N13NO001O010000O10O11O5K1N10201N5J11N2N1O4K6K5J4L2N101N2O4]\\OhMdb0\\3G4M2M3d^ObL_?X4T_O\\Ll`0e43L1N1N3N2N1N2N2O3L3M2N2XLe^OW2]a0\\MZ_OY2l`0ZM__Oa2^b0K5K4OOM4L4L3M4L3M3M2N2N2J6M3N1O3L4M2N1N3N2N2N1N01O00010O001O010000000Zao3"
          },
          "bbox": [
            730.0,
            194.0,
            841.0,
            469.0
          ]
        }
      },
      {
        "tree_index": "4-0",
        "image_path": "/home/utkarsh/TreeInventorization/data/views/sYtn_I1t9YjHvONbMdcb0w_view6_tree0_box6.jpg",
        "confidence": 0.012153277173638344,
        "mask_data": {
          "orig_shape": [
            720,
            1024
          ],
          "encoding": "rle",
          "rle": {
            "size": [
              720,
              1024
            ],
            "counts": "mh^>V1Ze00000001O3M4L4K6J7E9L3M2N2N4L3M3M7I4L1O2N1O2N2NcMV]OU1ib0hN_]OU1_b0gNi]OX1Tb0eNS^OZ1ja0dN\\^OZ1ba0eNb^O[1[a0bNm^O]1o`0aNX_O]1e`0aN`_O`1\\`0_Nh_Oc1S`0[NR@g1i?WN[@j1b?UNa@k1]?TNf@l1Qb0O000O10f\\OTNna0l1o]O\\Nla0e1P^O`Noa0_1o]OcNSb0\\1j]OeNYb0Z1e]OgN\\b0X1d]OiN[b0X1b]OjN_b0V1_]OjNeb0U1X]OkNjb0V1S]OjNob0V1m\\OmNTc0W22N101N1O2N1O002N100O10O011O0O3NO1O1O1O2O010N10102N000O20106IO0O1O3L6J4NdM`\\Oe1Wd01M2N001O0O1001O1N2N;E4L4L3L4M8G4M1N3M3L4L3LiUb5"
          },
          "bbox": [
            658.0,
            118.0,
            769.0,
            445.0
          ]
        }
      }
    ],
    "view_7": [
      {
        "tree_index": "5-0",
        "image_path": "/home/utkarsh/TreeInventorization/data/views/sYtn_I1t9YjHvONbMdcb0w_view7_tree0_box3.jpg",
        "confidence": 0.017899246886372566,
        "mask_data": {
          "orig_shape": [
            720,
            1024
          ],
          "encoding": "rle",
          "rle": {
            "size": [
              720,
              1024
            ],
            "counts": "nfS6b0m00bc00^\\O0bc00^\\O0bc00^\\O0bc01]\\O0bc00]\\O8\\c0Ia\\Ob0Vc0_Oh\\Of0Tc0\\Oi\\OT1hb0mNX]O]1]b0eNb]Oc1Ub0]Nl]Om1ia0UNT^O]2[a0eMb^Oc2Wa0_Mf^Ob2Za0bM`^O`2`a0X10000000000000TNQ_OWNo`0c1\\_OXNd`0e1a_OYN_`0d1j_OVNV`0f1Q@WNo?f1V@QNQ`0l1Z@gMk?V2Y2M3M3M3N2N2O1M3N2O1N2O1N2N2O1N2N2N2O100000RgW?"
          },
          "bbox": [
            278.0,
            254.0,
            329.0,
            409.0
          ]
        }
      }
    ],
    "view_12": [
      {
        "tree_index": "6-0",
        "image_path": "/home/utkarsh/TreeInventorization/data/views/sYtn_I1t9YjHvONbMdcb0w_view12_tree0_box0.jpg",
        "confidence": 0.030286001041531563,
        "mask_data": {
          "orig_shape": [
            720,
            1024
          ],
          "encoding": "rle",
          "rle": {
            "size": [
              720,
              1024
            ],
            "counts": "VRe;f0je00000001O3M4M1N2N4J:E;F5K5K6F9M3M2N2N2N3M4L3M2N3M2N2N2N5K_MZ]OZ1db0aNg]O[1Wb0cNo]O[1oa0eNT^OZ1ja0eNZ^O[1ca0eN`^O[1]a0eNi^OX1`a0\\Nc^Od1ia0lM\\^OU2Qc0200L2N100O1O0O2O100N2N1O2N2O2M5J7I9F;E;E9G1N2M3VOj0bN^1I7]Oc0000000000000000000000000000hN[AfIMi0h>^5gA_JY>^5lA`JT>^5VBZJj=Y1cAU2g0`Lf=b0aASOa0e3=\\Lh=3UC\\3k`0J6gMQ]Og0Yc0fNa]Oh0_kl8"
          },
          "bbox": [
            530.0,
            406.0,
            618.0,
            649.0
          ]
        }
      },
      {
        "tree_index": "7-0",
        "image_path": "/home/utkarsh/TreeInventorization/data/views/sYtn_I1t9YjHvONbMdcb0w_view12_tree0_box1.jpg",
        "confidence": 0.010581162758171558,
        "mask_data": {
          "orig_shape": [
            720,
            1024
          ],
          "encoding": "rle",
          "rle": {
            "size": [
              720,
              1024
            ],
            "counts": "j[Tf0a080kd0S1H4U]OaN^`0d1\\_O_Nb`0f1Y_O[Nf`0i1U_OZNi`0h1U_OYNg`0m1U_OUNk`0m1R_OSNo`0P2m^OQNSa0Q2d^O]M[Oa0Rb0U2[^OVNfa0n1Q^OXNna0V3O1O000RF"
          },
          "bbox": [
            1007.0,
            318.0,
            1023.0,
            456.0
          ]
        }
      }
    ]
  },
  "metadata": {
    "total_views": 4,
    "total_masks": 8
  }
}